library/__init__.py
library/hello.py
giangitestpkg-0.0.1.dist-info/METADATA
giangitestpkg-0.0.1.dist-info/WHEEL
giangitestpkg-0.0.1.dist-info/top_level.txt
giangitestpkg-0.0.1.dist-info/RECORD
