Metadata-Version: 2.1
Name: giangitestpkg
Version: 0.0.1
Summary: test pkg
Author: Gianluca
Author-email: <viogianluca77@gmail.com>
Keywords: python
Classifier: Development Status :: 1 - Planning
Classifier: Intended Audience :: Developers
Classifier: Programming Language :: Python :: 3
Classifier: Operating System :: Unix
Classifier: Operating System :: MacOS :: MacOS X
Classifier: Operating System :: Microsoft :: Windows
Requires-Dist: wheel
